{
  "model": "Meta-Llama-3-8B-Instruct",
  "task": "LaMP-5",
  "top_percent": 0.04,
  "num_heads_selected": 40,
  "preference_heads": [
    [
      31,
      11
    ],
    [
      16,
      14
    ],
    [
      17,
      14
    ],
    [
      16,
      6
    ],
    [
      1,
      31
    ],
    [
      1,
      27
    ],
    [
      30,
      2
    ],
    [
      7,
      9
    ],
    [
      10,
      8
    ],
    [
      9,
      11
    ],
    [
      3,
      4
    ],
    [
      6,
      22
    ],
    [
      15,
      14
    ],
    [
      26,
      14
    ],
    [
      1,
      18
    ],
    [
      7,
      3
    ],
    [
      25,
      2
    ],
    [
      29,
      13
    ],
    [
      9,
      28
    ],
    [
      1,
      17
    ],
    [
      21,
      14
    ],
    [
      30,
      12
    ],
    [
      8,
      8
    ],
    [
      12,
      4
    ],
    [
      13,
      14
    ],
    [
      17,
      6
    ],
    [
      6,
      5
    ],
    [
      10,
      24
    ],
    [
      1,
      12
    ],
    [
      25,
      14
    ],
    [
      7,
      23
    ],
    [
      16,
      9
    ],
    [
      4,
      10
    ],
    [
      6,
      26
    ],
    [
      12,
      3
    ],
    [
      14,
      20
    ],
    [
      30,
      8
    ],
    [
      7,
      11
    ],
    [
      10,
      13
    ],
    [
      28,
      27
    ]
  ]
}